simpleGPyT/__init__.py
simpleGPyT/simpleGPyT.py
simpleGpyT-0.1.5.dist-info/LICENSE
simpleGpyT-0.1.5.dist-info/METADATA
simpleGpyT-0.1.5.dist-info/WHEEL
simpleGpyT-0.1.5.dist-info/top_level.txt
simpleGpyT-0.1.5.dist-info/RECORD
