Metadata-Version: 2.1
Name: simpleGpyT
Version: 0.1.5
Summary: A simplified object-oriented interface for OpenAI's chat completion API.
Home-page: https://github.com/AJWestley/SimpleChat
Author: AJ Westley
Author-email: <alexanderjwestley@gmail.com>
Classifier: Development Status :: 4 - Beta
Classifier: Intended Audience :: Developers
Classifier: Programming Language :: Python :: 3.10
Classifier: Operating System :: OS Independent
License-File: LICENSE
Requires-Dist: openai >=0.28.0
